odoo/addons/stock_picking_quick/README.rst
odoo/addons/stock_picking_quick/__init__.py
odoo/addons/stock_picking_quick/__manifest__.py
odoo/addons/stock_picking_quick/i18n/pt_BR.po
odoo/addons/stock_picking_quick/i18n/stock_picking_quick.pot
odoo/addons/stock_picking_quick/models/__init__.py
odoo/addons/stock_picking_quick/models/product_product.py
odoo/addons/stock_picking_quick/models/stock_picking.py
odoo/addons/stock_picking_quick/readme/CONTRIBUTORS.rst
odoo/addons/stock_picking_quick/readme/DESCRIPTION.rst
odoo/addons/stock_picking_quick/readme/USAGE.rst
odoo/addons/stock_picking_quick/static/description/filter.png
odoo/addons/stock_picking_quick/static/description/icon.png
odoo/addons/stock_picking_quick/static/description/index.html
odoo/addons/stock_picking_quick/static/description/po-product.png
odoo/addons/stock_picking_quick/static/description/po.png
odoo/addons/stock_picking_quick/tests/__init__.py
odoo/addons/stock_picking_quick/tests/test_stock_picking_quick.py
odoo/addons/stock_picking_quick/views/picking_view.xml
odoo/addons/stock_picking_quick/views/product_view.xml
odoo12_addon_stock_picking_quick-12.0.1.0.3.dist-info/METADATA
odoo12_addon_stock_picking_quick-12.0.1.0.3.dist-info/WHEEL
odoo12_addon_stock_picking_quick-12.0.1.0.3.dist-info/top_level.txt
odoo12_addon_stock_picking_quick-12.0.1.0.3.dist-info/RECORD
